mundey/__init__.py
mundey/mundey.py
mundey/data/tess-undershoot.xml
mundey-0.1.1.5.dist-info/LICENSE
mundey-0.1.1.5.dist-info/METADATA
mundey-0.1.1.5.dist-info/WHEEL
mundey-0.1.1.5.dist-info/top_level.txt
mundey-0.1.1.5.dist-info/RECORD
